<?xml version="1.0" encoding="utf-8" ?>
<Items>
	<IdentifiedItem>
		<Name>Copper coin</Name>
		<Description>A coin made from copper, from a local mint.</Description>
		<Value>1</Value>
		<Material>Copper</Material>
		<Size>1</Size>
		<SpawnWeight>50</SpawnWeight>
		<Tag>currency</Tag>
		<Tileset>Currency</Tileset>
	</IdentifiedItem>

	<IdentifiedItem>
		<Name>Silver coin</Name>
		<Description>A coin made from shiny silver, from a local mint.</Description>
		<Value>10</Value>
		<Material>Silver</Material>
		<Size>1</Size>
		<SpawnWeight>30</SpawnWeight>
		<Tag>currency</Tag>
		<Tileset>Currency</Tileset>
	</IdentifiedItem>

	<IdentifiedItem>
		<Name>Gold coin</Name>
		<Description>A valuable gold coin, from a local mint.</Description>
		<Value>100</Value>
		<Material>Gold</Material>
		<Size>1</Size>
		<SpawnWeight>5</SpawnWeight>
		<Tag>currency</Tag>
		<Tileset>Currency</Tileset>
	</IdentifiedItem>

	<TileSet>
		<Filename>Money</Filename>
		<Name>Currency</Name>
		<SpriteData>
			<Name>copper coin</Name>
			<Part>
				<Name>copper coin</Name>
				<Filename>Money32</Filename>
				<Data>default</Data>
				<Position>0</Position>
				<Colour>#ff851bff</Colour>
			</Part>
		</SpriteData>
		<SpriteData>
			<Name>silver coin</Name>
			<Part>
				<Name>silver coin</Name>
				<Filename>Money32</Filename>
				<Data>default</Data>
				<Position>0</Position>
				<Colour>#d9d9d9ff</Colour>
			</Part>
		</SpriteData>
		<SpriteData>
			<Name>gold coin</Name>
			<Part>
				<Name>gold coin</Name>
				<Filename>Money32</Filename>
				<Data>default</Data>
				<Position>0</Position>
				<Colour>#ffc80aff</Colour>
			</Part>
		</SpriteData>
	</TileSet>
</Items>